recent2.py
recent2-1.0.2.dist-info/LICENSE
recent2-1.0.2.dist-info/METADATA
recent2-1.0.2.dist-info/WHEEL
recent2-1.0.2.dist-info/entry_points.txt
recent2-1.0.2.dist-info/top_level.txt
recent2-1.0.2.dist-info/RECORD
