Metadata-Version: 2.1
Name: recent2
Version: 1.0.2
Summary: Logs bash history to an sqlite database
Home-page: https://github.com/dotslash/recent2
License: MIT
Keywords: logging bash history database sqlite
Platform: UNKNOWN
Classifier: Development Status :: 4 - Beta
Classifier: Intended Audience :: Developers
Classifier: Environment :: Console
Classifier: Topic :: System :: Logging
Classifier: Topic :: System :: Shells
Classifier: Topic :: Utilities
Classifier: License :: OSI Approved :: MIT License
Classifier: Programming Language :: Python :: 3 :: Only
Requires-Python: >=3
Requires-Dist: tabulate
